example/__init__.py
example/example.py
mapflow_sdk/__init__.py
mapflow_sdk/base/__init__.py
mapflow_sdk/base/server.py
mapflow_sdk/base/utils.py
mapflow_sdk/entity/__init__.py
mapflow_sdk/entity/aoi.py
mapflow_sdk/entity/enums.py
mapflow_sdk/entity/error_message.py
mapflow_sdk/entity/model.py
mapflow_sdk/entity/processing.py
mapflow_sdk/entity/project.py
mapflow_sdk/entity/provider.py
mapflow_sdk/entity/user.py
mapflow_sdk/io/__init__.py
mapflow_sdk/io/vector.py
mapflow_sdk/rest/__init__.py
mapflow_sdk/rest/processing.py
mapflow_sdk/rest/project.py
mapflow_sdk/rest/user.py
mapflow_sdk-2.1.0b1.dist-info/LICENSE
mapflow_sdk-2.1.0b1.dist-info/METADATA
mapflow_sdk-2.1.0b1.dist-info/WHEEL
mapflow_sdk-2.1.0b1.dist-info/top_level.txt
mapflow_sdk-2.1.0b1.dist-info/RECORD
