Metadata-Version: 2.1
Name: mapflow-sdk
Version: 2.1.0b1
Summary: Python library for easy acceess to Mapflow API
Home-page: https://github.com/geoalert/mapflow-sdk
Author: Geoalert
Author-email: hello@geoalert.io
License: MIT
Classifier: License :: OSI Approved :: MIT License
Classifier: Programming Language :: Python
Classifier: Programming Language :: Python :: 3
Classifier: Programming Language :: Python :: 3.6
Classifier: Programming Language :: Python :: Implementation :: CPython
Classifier: Programming Language :: Python :: Implementation :: PyPy
Requires-Python: >=3.8.0
License-File: LICENSE
Requires-Dist: pydantic (~=2.1.1)
Requires-Dist: requests (~=2.31.0)
Requires-Dist: pydantic-geojson
